ezhc/__init__.py
ezhc/__meta__.py
ezhc/_clock.py
ezhc/_config.py
ezhc/_global_options.py
ezhc/_hc_versions.py
ezhc/_highcharts.py
ezhc/_highstock.py
ezhc/_img.py
ezhc/_plot.py
ezhc/_proxy.py
ezhc/_state.py
ezhc/_theme.py
ezhc/_wrapper.py
ezhc/build.py
ezhc/sample.py
ezhc/scripts.py
ezhc/series.py
ezhc/api/hc_object.json
ezhc/api/hc_option.json
ezhc/api/hs_object.json
ezhc/api/hs_option.json
ezhc/samples/df_bubble.csv
ezhc/samples/df_heatmap.csv
ezhc/samples/df_one_idx_one_col.csv
ezhc/samples/df_one_idx_several_col.csv
ezhc/samples/df_one_idx_several_col_2.csv
ezhc/samples/df_one_idx_two_col.csv
ezhc/samples/df_scatter.csv
ezhc/samples/df_several_idx_one_col.csv
ezhc/samples/df_several_idx_one_col_2.csv
ezhc/samples/df_two_idx_one_col.csv
ezhc/samples/df_two_idx_several_col.csv
ezhc/script/Jupyter_logo.png
ezhc/script/SG_logo.png
ezhc/script/financial_time_series_0.js
ezhc/script/financial_time_series_table.html
ezhc/script/financial_time_series_table_1.js
ezhc/script/financial_time_series_table_2.js
ezhc/script/financial_time_series_table_options_1.js
ezhc/script/financial_time_series_table_options_2.js
ezhc/script/formatter_basic.js
ezhc/script/formatter_percent.js
ezhc/script/formatter_quantile.js
ezhc/script/json_parse.js
ezhc/script/template_disclaimer.html
ezhc/script/tooltip_positioner_center_top.js
ezhc/script/tooltip_positioner_left_top.js
ezhc/script/tooltip_positioner_right_top.js
ezhc/script/themes/avocado.js
ezhc/script/themes/avocado.json
ezhc/script/themes/build_theme_json.ipynb
ezhc/script/themes/dark-blue.js
ezhc/script/themes/dark-blue.json
ezhc/script/themes/dark-green.js
ezhc/script/themes/dark-green.json
ezhc/script/themes/dark-unica.js
ezhc/script/themes/dark-unica.json
ezhc/script/themes/gray.js
ezhc/script/themes/gray.json
ezhc/script/themes/grid-light.js
ezhc/script/themes/grid-light.json
ezhc/script/themes/grid.js
ezhc/script/themes/grid.json
ezhc/script/themes/sand-signika.js
ezhc/script/themes/sand-signika.json
ezhc-0.7.12.dist-info/LICENSE
ezhc-0.7.12.dist-info/METADATA
ezhc-0.7.12.dist-info/WHEEL
ezhc-0.7.12.dist-info/top_level.txt
ezhc-0.7.12.dist-info/RECORD
