Metadata-Version: 2.1
Name: ezhc
Version: 0.7.12
Summary: easy Highcharts & Highstock, dynamic plots from pandas dataframes in the Jupyter notebook
Home-page: https://github.com/oscar6echo/ezhc
Download-URL: https://github.com/oscar6echo/ezhc/tarball/0.7.12
Author: oscar6echo
Author-email: olivier.borderies@gmail.com
License: MIT
Keywords: Highcharts,Highstock,pandas,notebook,javascript
Classifier: Development Status :: 4 - Beta
Classifier: License :: OSI Approved :: MIT License
Classifier: Programming Language :: Python :: 2.7
Classifier: Programming Language :: Python :: 3.5
Classifier: Programming Language :: Python :: 3.6
Classifier: Programming Language :: Python :: 3.7
Classifier: Programming Language :: Python :: 3.8
License-File: LICENSE
Requires-Dist: pandas >=0.17
Requires-Dist: jinja2 >=2.8
Requires-Dist: ipython >=3.0
Requires-Dist: requests >=2.9
